action_engine-0.2.0.dist-info/WHEEL
action_engine-0.2.0.dist-info/entry_points.txt
action_engine-0.2.0.dist-info/METADATA
actionengine/service.py
actionengine/webrtc.py
actionengine/websockets.py
actionengine/status.cpython-312-darwin.so
actionengine/session.py
actionengine/actions.py
actionengine/__init__.py
actionengine/global_settings.py
actionengine/stream.py
actionengine/async_node.py
actionengine/cli.py
actionengine/redis.py
actionengine/utils.py
actionengine/_C.cpython-312-darwin.so
actionengine/node_map.py
actionengine/chunk_store.py
actionengine/data.py
actionengine/pydantic_helpers.py
actionengine/proto/__init__.py
actionengine/proto/types_pb2.py
actionengine/cli/auth.py
actionengine/cli/__init__.py
actionengine/cli/serve.py
actionengine/cli/utils.py
actionengine/cli/main.py
actionengine/_C/redis.pyi
actionengine/_C/data.pyi
actionengine/_C/__init__.pyi
actionengine/_C/nodes.pyi
actionengine/_C/actions.pyi
actionengine/_C/webrtc.pyi
actionengine/_C/chunk_store.pyi
actionengine/_C/service.pyi
actionengine/_C/websockets.pyi
action_engine-0.2.0.dist-info/RECORD
