Metadata-Version: 2.1
Name: action-engine
Version: 0.2.0
Requires-Dist: absl-py>=2.2.2
Requires-Dist: numpy>=2,<2.3.0
Requires-Dist: ormsgpack
Requires-Dist: Pillow
Requires-Dist: pydantic
Requires-Dist: pybind11>=2.13.6
